xxy/__about__.py
xxy/__init__.py
xxy/__main__.py
xxy/agent.py
xxy/chunker.py
xxy/chunker_provider.py
xxy/client.py
xxy/config.py
xxy/py.typed
xxy/rongda_agent.py
xxy/rongda_session.py
xxy/selector.py
xxy/stream.py
xxy/types.py
xxy/web.py
xxy/wsgi.py
xxy/agents/__init__.py
xxy/agents/analysis_agent.py
xxy/agents/search_agent.py
xxy/chatbot/404.html
xxy/chatbot/favicon.ico
xxy/chatbot/file.svg
xxy/chatbot/globe.svg
xxy/chatbot/index.html
xxy/chatbot/index.txt
xxy/chatbot/next.svg
xxy/chatbot/vercel.svg
xxy/chatbot/window.svg
xxy/chatbot/_next/static/GULXWlkiDGnJupz7EcPO3/_buildManifest.js
xxy/chatbot/_next/static/GULXWlkiDGnJupz7EcPO3/_ssgManifest.js
xxy/chatbot/_next/static/chunks/146-8bff6ac94759de36.js
xxy/chatbot/_next/static/chunks/4bd1b696-2d14aed30f780de7.js
xxy/chatbot/_next/static/chunks/684-6afe575ea30c3161.js
xxy/chatbot/_next/static/chunks/framework-f593a28cde54158e.js
xxy/chatbot/_next/static/chunks/main-a8bb89d6e4968bfb.js
xxy/chatbot/_next/static/chunks/main-app-77a818c18c218a43.js
xxy/chatbot/_next/static/chunks/polyfills-42372ed130431b0a.js
xxy/chatbot/_next/static/chunks/webpack-26f06335671aaa1d.js
xxy/chatbot/_next/static/chunks/app/layout-78286e6b0e548493.js
xxy/chatbot/_next/static/chunks/app/page-ceba3bdbc0cce4a5.js
xxy/chatbot/_next/static/chunks/app/_not-found/page-da10007f1625fcc9.js
xxy/chatbot/_next/static/chunks/pages/_app-da15c11dea942c36.js
xxy/chatbot/_next/static/chunks/pages/_error-cc3f077a18ea1793.js
xxy/chatbot/_next/static/css/326aeaa7d8871bbf.css
xxy/chatbot/_next/static/media/569ce4b8f30dc480-s.p.woff2
xxy/chatbot/_next/static/media/747892c23ea88013-s.woff2
xxy/chatbot/_next/static/media/8d697b304b401681-s.woff2
xxy/chatbot/_next/static/media/93f479601ee12b01-s.p.woff2
xxy/chatbot/_next/static/media/9610d9e46709d722-s.woff2
xxy/chatbot/_next/static/media/ba015fad6dcf6784-s.woff2
xxy/context/pdf.py
xxy/data_source/__init__.py
xxy/data_source/base.py
xxy/data_source/folder.py
xxy/data_source/rongda.py
xxy/result_writer/__init__.py
xxy-4574.3.3.dist-info/METADATA
xxy-4574.3.3.dist-info/WHEEL
xxy-4574.3.3.dist-info/entry_points.txt
xxy-4574.3.3.dist-info/licenses/LICENSE
xxy-4574.3.3.dist-info/RECORD
