Metadata-Version: 2.4
Name: xxy
Version: 4574.3.3
Summary: A financial statement analysis tool
Project-URL: homepage, https://github.com/iaalm/xxy
Project-URL: repository, https://github.com/iaalm/xxy
Project-URL: documentation, https://github.com/iaalm/xxy
Author-email: iaalm <iaalmsimon@gmail.com>
License: MIT
License-File: LICENSE
Keywords: finance,llm
Classifier: Development Status :: 4 - Beta
Classifier: Intended Audience :: Science/Research
Classifier: License :: OSI Approved :: MIT License
Classifier: Programming Language :: Python :: 3 :: Only
Requires-Python: >=3.12
Requires-Dist: fastapi>=0.104.0
Requires-Dist: langchain
Requires-Dist: langchain-openai
Requires-Dist: langchain-text-splitters
Requires-Dist: langgraph
Requires-Dist: llama-index
Requires-Dist: llama-index-embeddings-azure-openai
Requires-Dist: llama-index-retrievers-bm25
Requires-Dist: loguru
Requires-Dist: pydantic
Requires-Dist: rongda-mcp-server>=0.3.0
Requires-Dist: uvicorn[standard]>=0.24.0
Provides-Extra: all
Requires-Dist: pdfplumber; extra == 'all'
Provides-Extra: pdf
Requires-Dist: pdfplumber; extra == 'pdf'
